flet_model/__init__.py
flet_model/model.py
flet_model/router.py
flet_model-0.1.5.dist-info/METADATA
flet_model-0.1.5.dist-info/WHEEL
flet_model-0.1.5.dist-info/licenses/LICENSE
flet_model-0.1.5.dist-info/RECORD
