Metadata-Version: 2.4
Name: flet-model
Version: 0.1.5
Summary: A Model-based router for Flet applications that simplifies the creation of multi-page applications
Project-URL: Homepage, https://github.com/fasilwdr/Flet-Model
Project-URL: Documentation, https://github.com/fasilwdr/Flet-Model#readme
Project-URL: Repository, https://github.com/fasilwdr/Flet-Model.git
Project-URL: Issues, https://github.com/fasilwdr/Flet-Model/issues
Project-URL: Changelog, https://github.com/fasilwdr/Flet-Model/releases
Author-email: Fasil <fasilwdr@hotmail.com>
License: MIT License
License-File: LICENSE
Keywords: flet,framework,gui,model,mvc,navigation,router,ui
Classifier: Development Status :: 3 - Alpha
Classifier: Intended Audience :: Developers
Classifier: License :: OSI Approved :: MIT License
Classifier: Operating System :: OS Independent
Classifier: Programming Language :: Python
Classifier: Programming Language :: Python :: 3
Classifier: Programming Language :: Python :: 3.7
Classifier: Programming Language :: Python :: 3.8
Classifier: Programming Language :: Python :: 3.9
Classifier: Programming Language :: Python :: 3.10
Classifier: Programming Language :: Python :: 3.11
Classifier: Topic :: Software Development :: Libraries :: Python Modules
Classifier: Topic :: Software Development :: User Interfaces
Requires-Python: >=3.7
Requires-Dist: flet>=0.10.0
Provides-Extra: dev
Requires-Dist: black; extra == 'dev'
Requires-Dist: build; extra == 'dev'
Requires-Dist: flake8; extra == 'dev'
Requires-Dist: isort; extra == 'dev'
Requires-Dist: mypy; extra == 'dev'
Requires-Dist: pytest-cov; extra == 'dev'
Requires-Dist: pytest>=7.0.0; extra == 'dev'
Requires-Dist: sphinx; extra == 'dev'
Requires-Dist: sphinx-rtd-theme; extra == 'dev'
Requires-Dist: twine; extra == 'dev'
